{
  "configs": [
    "wmg-music-factory-api.xml"
  ],
  "secureProperties": [
    "anypoint.platform.client_id",
    "anypoint.platform.client_secret"
  ],
  "redeploymentEnabled": true,
  "name": "com.mycompany:wmg-music-factory-api:1.0.0-SNAPSHOT",
  "minMuleVersion": "4.3.0",
  "requiredProduct": "MULE_EE",
  "classLoaderModelLoaderDescriptor": {
    "id": "mule",
    "attributes": {
      "exportedPackages": [],
      "exportedResources": [
        "local.properties",
        "log4j2.xml",
        "wmg-music-factory-api.xml"
      ]
    }
  },
  "bundleDescriptorLoader": {
    "id": "mule",
    "attributes": {}
  }
}